zuup/__init__.py
zuup/tests/__init__.py
zuup/tests/base.py
zuup/tests/test_zuup.py
zuup-1.0.7.dist-info/DESCRIPTION.rst
zuup-1.0.7.dist-info/METADATA
zuup-1.0.7.dist-info/RECORD
zuup-1.0.7.dist-info/WHEEL
zuup-1.0.7.dist-info/entry_points.txt
zuup-1.0.7.dist-info/metadata.json
zuup-1.0.7.dist-info/pbr.json
zuup-1.0.7.dist-info/top_level.txt
