Metadata-Version: 2.0
Name: zuup
Version: 1.0.7
Summary: Command line to consult Openstack zuul status
Home-page: https://github.com/sileht/zuup
Author: Mehdi Abaakouk
Author-email: sileht@sileht.net
License: UNKNOWN
Platform: UNKNOWN
Classifier: Environment :: OpenStack
Classifier: Intended Audience :: Information Technology
Classifier: Intended Audience :: System Administrators
Classifier: License :: OSI Approved :: Apache Software License
Classifier: Operating System :: POSIX :: Linux
Classifier: Programming Language :: Python
Classifier: Programming Language :: Python :: 2
Classifier: Programming Language :: Python :: 2.7
Classifier: Programming Language :: Python :: 3
Classifier: Programming Language :: Python :: 3.3
Classifier: Programming Language :: Python :: 3.4
Requires-Dist: Babel (>=1.3)
Requires-Dist: pbr (<2.0,>=1.4)
Requires-Dist: requests
